[
  {
    "outputFile": "assets/css/Admin/_layout.css",
    "inputFile": "assets/css/Admin/_layout.less"
  },
  {
    "outputFile": "assets/css/Admin/Home/Index.css",
    "inputFile": "assets/css/Admin/Home/Index.less"
  },
  {
    "outputFile": "assets/css/Admin/_iframe.layout.css",
    "inputFile": "assets/css/Admin/_iframe.layout.less"
  },
  {
    "outputFile": "assets/css/Admin/left-menu.css",
    "inputFile": "assets/css/Admin/left-menu.less"
  },
  {
    "outputFile": "assets/css/Admin/nav-menu.css",
    "inputFile": "assets/css/Admin/nav-menu.less"
  },
  {
    "outputFile": "assets/css/Admin/timeline.css",
    "inputFile": "assets/css/Admin/timeline.less"
  },
  {
    "outputFile": "assets/css/Admin/_app.layout.css",
    "inputFile": "assets/css/Admin/_app.layout.less"
  }
]